simplebooks/__init__.py
simplebooks/version.py
simplebooks/asyncql/Account.py
simplebooks/asyncql/AccountCategory.py
simplebooks/asyncql/AccountType.py
simplebooks/asyncql/ArchivedEntry.py
simplebooks/asyncql/ArchivedTransaction.py
simplebooks/asyncql/Currency.py
simplebooks/asyncql/Customer.py
simplebooks/asyncql/Entry.py
simplebooks/asyncql/EntryType.py
simplebooks/asyncql/Identity.py
simplebooks/asyncql/Ledger.py
simplebooks/asyncql/LedgerType.py
simplebooks/asyncql/Statement.py
simplebooks/asyncql/Transaction.py
simplebooks/asyncql/Vendor.py
simplebooks/asyncql/__init__.py
simplebooks/models/Account.py
simplebooks/models/AccountCategory.py
simplebooks/models/AccountType.py
simplebooks/models/ArchivedEntry.py
simplebooks/models/ArchivedTransaction.py
simplebooks/models/Currency.py
simplebooks/models/Customer.py
simplebooks/models/Entry.py
simplebooks/models/EntryType.py
simplebooks/models/Identity.py
simplebooks/models/Ledger.py
simplebooks/models/LedgerType.py
simplebooks/models/Statement.py
simplebooks/models/Transaction.py
simplebooks/models/Vendor.py
simplebooks/models/__init__.py
simplebooks-0.3.2.dist-info/METADATA
simplebooks-0.3.2.dist-info/WHEEL
simplebooks-0.3.2.dist-info/RECORD
